.DS_Store
Taby/__init__.py
Taby/console.py
Taby/highlighter.py
Taby/reader.py
Taby-1.0.0.dist-info/LICENSE.txt
Taby-1.0.0.dist-info/METADATA
Taby-1.0.0.dist-info/WHEEL
Taby-1.0.0.dist-info/top_level.txt
Taby-1.0.0.dist-info/RECORD
