Metadata-Version: 2.1
Name: Taby
Version: 1.0.0
Summary: CLI for highlighting tab spaces in a file
Home-page: UNKNOWN
Author: Sombodee (Landon Hutchins)
License: MIT
Keywords: python,tabs,highlight,CLI
Platform: UNKNOWN
Classifier: Programming Language :: Python :: 3
Classifier: Operating System :: Unix
Classifier: Operating System :: MacOS :: MacOS X
Classifier: Operating System :: Microsoft :: Windows
